{
  "categories": [
    {
      "id": 1,
      "name": "Cameras",
      "subcategories": []
    },
    {
      "id": 2,
      "name": "Electronics",
      "subcategories": [
        "Accessories",
        "Audio & Video",
        "Camera & Photo",
        "Laptops"
      ]
    },
    {
      "id": 3,
      "name": "Fashion",
      "subcategories": ["Kids Fashion", "Man", "Woman"]
    },
    {
      "id": 4,
      "name": "Furniture",
      "subcategories": []
    },
    {
      "id": 5,
      "name": "Gaming",
      "subcategories": []
    }
  ],
  "priceRange": {
    "min": 0,
    "max": 1000
  },
  "colors": ["#000000", "#0188cc", "#81d742", "#6085a5", "#ab6e6e"],
  "brands": ["Adidas", "Asics", "Brooks", "Nike", "Puma"]
}
